{
    "form_name": "blue-striped",
    "form_order": 2,
    "id": 10066,
    "is_battle_only": false,
    "is_default": true,
    "is_mega": false,
    "name": "basculin-blue-striped",
    "order": 656,
    "pokemon": {
        "name": "basculin-blue-striped",
        "url": "http://127.0.0.1:8000/api/v2/pokemon/10016/"
    },
    "sprites": {
        "back_default": "http://127.0.0.1:8000/media/sprites/pokemon/back/550-blue-striped.png",
        "back_shiny": "http://127.0.0.1:8000/media/sprites/pokemon/back/shiny/550-blue-striped.png",
        "front_default": "http://127.0.0.1:8000/media/sprites/pokemon/550-blue-striped.png",
        "front_shiny": "http://127.0.0.1:8000/media/sprites/pokemon/shiny/550-blue-striped.png"
    },
    "version_group": {
        "name": "black-white",
        "url": "http://127.0.0.1:8000/api/v2/version-group/11/"
    }
}
