{
    "form_name": "",
    "form_names": [],
    "form_order": 1,
    "id": 839,
    "is_battle_only": false,
    "is_default": true,
    "is_mega": false,
    "name": "coalossal",
    "names": [],
    "order": 1179,
    "pokemon": {
        "name": "coalossal",
        "url": "/api/v2/pokemon/839/"
    },
    "sprites": {
        "back_default": "https://raw.githubusercontent.com/PokeAPI/sprites/master/sprites/pokemon/back/839.png",
        "back_female": null,
        "back_shiny": "https://raw.githubusercontent.com/PokeAPI/sprites/master/sprites/pokemon/back/shiny/839.png",
        "back_shiny_female": null,
        "front_default": "https://raw.githubusercontent.com/PokeAPI/sprites/master/sprites/pokemon/839.png",
        "front_female": null,
        "front_shiny": "https://raw.githubusercontent.com/PokeAPI/sprites/master/sprites/pokemon/shiny/839.png",
        "front_shiny_female": null
    },
    "types": [
        {
            "slot": 1,
            "type": {
                "name": "rock",
                "url": "/api/v2/type/6/"
            }
        },
        {
            "slot": 2,
            "type": {
                "name": "fire",
                "url": "/api/v2/type/10/"
            }
        }
    ],
    "version_group": {
        "name": "sword-shield",
        "url": "/api/v2/version-group/20/"
    }
}