{
    "form_name": "poison",
    "form_names": [
        {
            "language": {
                "name": "ja-Hrkt",
                "url": "/api/v2/language/1/"
            },
            "name": "\u3069\u304f\u30bf\u30a4\u30d7"
        },
        {
            "language": {
                "name": "fr",
                "url": "/api/v2/language/5/"
            },
            "name": "Poison"
        },
        {
            "language": {
                "name": "de",
                "url": "/api/v2/language/6/"
            },
            "name": "Gift"
        },
        {
            "language": {
                "name": "es",
                "url": "/api/v2/language/7/"
            },
            "name": "Tipo Veneno"
        },
        {
            "language": {
                "name": "it",
                "url": "/api/v2/language/8/"
            },
            "name": "Tipo Veleno"
        },
        {
            "language": {
                "name": "en",
                "url": "/api/v2/language/9/"
            },
            "name": "Poison Type"
        }
    ],
    "form_order": 4,
    "id": 10052,
    "is_battle_only": false,
    "is_default": false,
    "is_mega": false,
    "name": "arceus-poison",
    "names": [
        {
            "language": {
                "name": "fr",
                "url": "/api/v2/language/5/"
            },
            "name": "Arceus Poison"
        },
        {
            "language": {
                "name": "de",
                "url": "/api/v2/language/6/"
            },
            "name": "Arceus (Gift)"
        },
        {
            "language": {
                "name": "en",
                "url": "/api/v2/language/9/"
            },
            "name": "Poison Arceus"
        }
    ],
    "order": 646,
    "pokemon": {
        "name": "arceus",
        "url": "/api/v2/pokemon/493/"
    },
    "sprites": {
        "back_default": "https://raw.githubusercontent.com/PokeAPI/sprites/master/sprites/pokemon/back/493-poison.png",
        "back_female": null,
        "back_shiny": "https://raw.githubusercontent.com/PokeAPI/sprites/master/sprites/pokemon/back/shiny/493-poison.png",
        "back_shiny_female": null,
        "front_default": "https://raw.githubusercontent.com/PokeAPI/sprites/master/sprites/pokemon/493-poison.png",
        "front_female": null,
        "front_shiny": "https://raw.githubusercontent.com/PokeAPI/sprites/master/sprites/pokemon/shiny/493-poison.png",
        "front_shiny_female": null
    },
    "types": [
        {
            "slot": 1,
            "type": {
                "name": "poison",
                "url": "/api/v2/type/4/"
            }
        }
    ],
    "version_group": {
        "name": "diamond-pearl",
        "url": "/api/v2/version-group/8/"
    }
}